{
    "models": [
        {
            "modelOptions": {
                "type": "deep-learning",
                "name": "FC AE",
                "modelType": "reconstructive",
                "dataType": 1,
                "requiresPriorTraining": true,
                "calcThresholdsOn": "anomalous-validation-data",
                "isMultivariate": true,
                "outputsLabels": false,
                "hyperparameters": {
                    "neurons": {
                        "value": 32,
                        "type": "integer"
                    },
                    "windowSize": {
                        "value": 100,
                        "type": "integer"
                    },
                    "stepSize": {
                        "value": 1,
                        "type": "integer"
                    },
                    "epochs": {
                        "value": 50,
                        "type": "integer"
                    },
                    "learningRate": {
                        "value": 0.001,
                        "type": "real"
                    },
                    "minibatchSize": {
                        "value": 64,
                        "type": "integer"
                    },
                     "ratioTrainVal": {
                        "value": 0,
                        "type": "real"
                    },
                    "reconstructionErrorType": {
                        "value": "median point-wise values",
                        "type": "categorical"
                    },
                    "scoringFunction": {
                        "value": "aggregated-errors",
                        "type": "categorical"
                    }
                }
            }
        },
        {
            "modelOptions": {
                "type": "deep-learning",
                "name": "LSTM (reconstruction)",
                "modelType": "reconstructive",
                "dataType": 2,
                "requiresPriorTraining": true,
                "calcThresholdsOn": "anomalous-validation-data",
                "isMultivariate": true,
                "outputsLabels": false,
                "hyperparameters": {
                    "hiddenUnits": {
                        "value": 64,
                        "type": "integer"
                    },
                    "windowSize": {
                        "value": 100,
                        "type": "integer"
                    },
                    "stepSize": {
                        "value": 1,
                        "type": "integer"
                    },
                    "epochs": {
                        "value": 50,
                        "type": "integer"
                    },
                    "learningRate": {
                        "value": 0.001,
                        "type": "real"
                    },
                    "minibatchSize": {
                        "value": 64,
                        "type": "integer"
                    },
                     "ratioTrainVal": {
                        "value": 0,
                        "type": "real"
                    },
                    "reconstructionErrorType": {
                        "value": "median point-wise values",
                        "type": "categorical"
                    },
                    "scoringFunction": {
                        "value": "aggregated-errors",
                        "type": "categorical"
                    }
                }
            }
        },
        {
            "modelOptions": {
                "type": "deep-learning",
                "name": "Hybrid CNN-LSTM (reconstruction)",
                "modelType": "reconstructive",
                "dataType": 2,
                "requiresPriorTraining": true,
                "calcThresholdsOn": "anomalous-validation-data",
                "isMultivariate": true,
                "outputsLabels": false,
                "hyperparameters": {
                    "hiddenUnits": {
                        "value": 64,
                        "type": "integer"
                    },
                    "filter": {
                        "value": 32,
                        "type": "integer"
                    },
                    "windowSize": {
                        "value": 100,
                        "type": "integer"
                    },
                    "stepSize": {
                        "value": 1,
                        "type": "integer"
                    },
                    "epochs": {
                        "value": 50,
                        "type": "integer"
                    },
                    "learningRate": {
                        "value": 0.001,
                        "type": "real"
                    },
                    "minibatchSize": {
                        "value": 64,
                        "type": "integer"
                    },
                     "ratioTrainVal": {
                        "value": 0,
                        "type": "real"
                    },
                    "reconstructionErrorType": {
                        "value": "median point-wise values",
                        "type": "categorical"
                    },
                    "scoringFunction": {
                        "value": "aggregated-errors",
                        "type": "categorical"
                    }
                }
            }
        },
        {
            "modelOptions": {
                "type": "deep-learning",
                "name": "TCN AE",
                "modelType": "reconstructive",
                "dataType": 2,
                "requiresPriorTraining": true,
                "calcThresholdsOn": "anomalous-validation-data",
                "isMultivariate": true,
                "outputsLabels": false,
                "hyperparameters": {
                    "filter": {
                        "value": 32,
                        "type": "integer"
                    },
                    "windowSize": {
                        "value": 100,
                        "type": "integer"
                    },
                    "stepSize": {
                        "value": 1,
                        "type": "integer"
                    },
                    "epochs": {
                        "value": 50,
                        "type": "integer"
                    },
                    "learningRate": {
                        "value": 0.001,
                        "type": "real"
                    },
                    "minibatchSize": {
                        "value": 64,
                        "type": "integer"
                    },
                     "ratioTrainVal": {
                        "value": 0,
                        "type": "real"
                    },
                    "reconstructionErrorType": {
                        "value": "median point-wise values",
                        "type": "categorical"
                    },
                    "scoringFunction": {
                        "value": "aggregated-errors",
                        "type": "categorical"
                    }
                }
            }
        },
        {
            "modelOptions": {
                "type": "deep-learning",
                "name": "LSTM",
                "modelType": "predictive",
                "dataType": 2,
                "requiresPriorTraining": true,
                "calcThresholdsOn": "anomalous-validation-data",
                "isMultivariate": true,
                "outputsLabels": false,
                "hyperparameters": {
                    "hiddenUnits": {
                        "value": 64,
                        "type": "integer"
                    },
                    "windowSize": {
                        "value": 100,
                        "type": "integer"
                    },
                    "stepSize": {
                        "value": 1,
                        "type": "integer"
                    },
                    "epochs": {
                        "value": 50,
                        "type": "integer"
                    },
                    "learningRate": {
                        "value": 0.001,
                        "type": "real"
                    },
                    "minibatchSize": {
                        "value": 64,
                        "type": "integer"
                    },
                     "ratioTrainVal": {
                        "value": 0,
                        "type": "real"
                    },
                    "scoringFunction": {
                        "value": "aggregated-errors",
                        "type": "categorical"
                    }
                }
            }
        },
        {
            "modelOptions": {
                "type": "deep-learning",
                "name": "Hybrid CNN-LSTM",
                "modelType": "predictive",
                "dataType": 2,
                "requiresPriorTraining": true,
                "calcThresholdsOn": "anomalous-validation-data",
                "isMultivariate": true,
                "outputsLabels": false,
                "hyperparameters": {
                    "hiddenUnits": {
                        "value": 64,
                        "type": "integer"
                    },
                    "filter": {
                        "value": 32,
                        "type": "integer"
                    },
                    "windowSize": {
                        "value": 100,
                        "type": "integer"
                    },
                    "stepSize": {
                        "value": 1,
                        "type": "integer"
                    },
                    "epochs": {
                        "value": 50,
                        "type": "integer"
                    },
                    "learningRate": {
                        "value": 0.001,
                        "type": "real"
                    },
                    "minibatchSize": {
                        "value": 64,
                        "type": "integer"
                    },
                     "ratioTrainVal": {
                        "value": 0,
                        "type": "real"
                    },
                    "scoringFunction": {
                        "value": "aggregated-errors",
                        "type": "categorical"
                    }
                }
            }
        },
        {
            "modelOptions": {
                "type": "deep-learning",
                "name": "GRU",
                "modelType": "predictive",
                "dataType": 2,
                "requiresPriorTraining": true,
                "calcThresholdsOn": "anomalous-validation-data",
                "isMultivariate": true,
                "outputsLabels": false,
                "hyperparameters": {
                    "hiddenUnits": {
                        "value": 64,
                        "type": "integer"
                    },
                    "windowSize": {
                        "value": 100,
                        "type": "integer"
                    },
                    "stepSize": {
                        "value": 1,
                        "type": "integer"
                    },
                    "epochs": {
                        "value": 50,
                        "type": "integer"
                    },
                    "learningRate": {
                        "value": 0.001,
                        "type": "real"
                    },
                    "minibatchSize": {
                        "value": 64,
                        "type": "integer"
                    },
                     "ratioTrainVal": {
                        "value": 0,
                        "type": "real"
                    },
                    "scoringFunction": {
                        "value": "aggregated-errors",
                        "type": "categorical"
                    }
                }
            }
        },
        {
            "modelOptions": {
                "type": "deep-learning",
                "name": "CNN (DeepAnT)",
                "modelType": "predictive",
                "dataType": 3,
                "requiresPriorTraining": true,
                "calcThresholdsOn": "anomalous-validation-data",
                "isMultivariate": true,
                "outputsLabels": false,
                "hyperparameters": {
                    "filter": {
                        "value": 8,
                        "type": "integer"
                    },
                    "windowSize": {
                        "value": 100,
                        "type": "integer"
                    },
                    "stepSize": {
                        "value": 1,
                        "type": "integer"
                    },
                    "epochs": {
                        "value": 50,
                        "type": "integer"
                    },
                    "learningRate": {
                        "value": 0.001,
                        "type": "real"
                    },
                    "minibatchSize": {
                        "value": 64,
                        "type": "integer"
                    },
                     "ratioTrainVal": {
                        "value": 0,
                        "type": "real"
                    },
                    "scoringFunction": {
                        "value": "aggregated-errors",
                        "type": "categorical"
                    }
                }
            }
        },
        {
            "modelOptions": {
                "type": "deep-learning",
                "name": "ResNet",
                "modelType": "predictive",
                "dataType": 3,
                "requiresPriorTraining": true,
                "calcThresholdsOn": "anomalous-validation-data",
                "isMultivariate": true,
                "outputsLabels": false,
                "hyperparameters": {
                    "filter": {
                        "value": 32,
                        "type": "integer"
                    },
                    "windowSize": {
                        "value": 100,
                        "type": "integer"
                    },
                    "stepSize": {
                        "value": 1,
                        "type": "integer"
                    },
                    "epochs": {
                        "value": 50,
                        "type": "integer"
                    },
                    "learningRate": {
                        "value": 0.001,
                        "type": "real"
                    },
                    "minibatchSize": {
                        "value": 64,
                        "type": "integer"
                    },
                     "ratioTrainVal": {
                        "value": 0,
                        "type": "real"
                    },
                    "scoringFunction": {
                        "value": "aggregated-errors",
                        "type": "categorical"
                    }
                }
            }
        },
        {
            "modelOptions": {
                "type": "deep-learning",
                "name": "MLP",
                "modelType": "predictive",
                "dataType": 1,
                "requiresPriorTraining": true,
                "calcThresholdsOn": "anomalous-validation-data",
                "isMultivariate": true,
                "outputsLabels": false,
                "hyperparameters": {
                    "neurons": {
                        "value": 32,
                        "type": "integer"
                    },
                    "windowSize": {
                        "value": 100,
                        "type": "integer"
                    },
                    "stepSize": {
                        "value": 1,
                        "type": "integer"
                    },
                    "epochs": {
                        "value": 50,
                        "type": "integer"
                    },
                    "learningRate": {
                        "value": 0.001,
                        "type": "real"
                    },
                    "minibatchSize": {
                        "value": 64,
                        "type": "integer"
                    },
                     "ratioTrainVal": {
                        "value": 0,
                        "type": "real"
                    },
                    "scoringFunction": {
                        "value": "aggregated-errors",
                        "type": "categorical"
                    }
                }
            }
        },
        {
            "modelOptions": {
                "type": "classic-machine-learning",
                "name": "iForest",
                "dataType": 1,
                "requiresPriorTraining": true,
                "calcThresholdsOn": "anomalous-validation-data",
                "isMultivariate": true,
                "outputsLabels": false,
                "useSubsequences": true,
                "hyperparameters": {
                    "numLearners": {
                        "value": 100,
                        "type": "integer"
                    },
                    "numObservationsPerLearner": {
                        "value": 128,
                        "type": "integer"
                    },
                    "windowSize": {
                        "value": 100,
                        "type": "integer"
                    }
                }
            }
        },
        {
            "modelOptions": {
                "type": "classic-machine-learning",
                "name": "OC-SVM",
                "dataType": 1,
                "requiresPriorTraining": true,
                "isMultivariate": true,
                "outputsLabels": true,
                "useSubsequences": true,
                "hyperparameters": {
                    "kernelFunction": {
                        "value": "gaussian",
                        "type": "categorical"
                    },
                    "windowSize": {
                        "value": 100,
                        "type": "integer"
                    }
                }
            }
        },
        {
            "modelOptions": {
                "type": "classic-machine-learning",
                "name": "ABOD",
                "dataType": 1,
                "requiresPriorTraining": false,
                "isMultivariate": true,
                "outputsLabels": false,
                "useSubsequences": true,
                "hyperparameters": {
                    "windowSize": {
                        "value": 100,
                        "type": "integer"
                    }
                }
            }
        },
        {
            "modelOptions": {
                "type": "classic-machine-learning",
                "name": "LOF",
                "dataType": 1,
                "requiresPriorTraining": false,
                "isMultivariate": true,
                "outputsLabels": false,
                "useSubsequences": true,
                "hyperparameters": {
                    "k": {
                        "value": 10,
                        "type": "integer"
                    },
                    "windowSize": {
                        "value": 100,
                        "type": "integer"
                    }
                }
            }
        },
        {
            "modelOptions": {
                "type": "classic-machine-learning",
                "name": "LDOF",
                "dataType": 1,
                "requiresPriorTraining": false,
                "isMultivariate": true,
                "outputsLabels": false,
                "useSubsequences": true,
                "hyperparameters": {
                    "k": {
                        "value": 10,
                        "type": "integer"
                    },
                    "windowSize": {
                        "value": 100,
                        "type": "integer"
                    }
                }
            }
        },
        {
            "modelOptions": {
                "type": "classic-machine-learning",
                "name": "Merlin",
                "requiresPriorTraining": false,
                "isMultivariate": false,
                "outputsLabels": true,
                "useSubsequences": false,
                "hyperparameters": {
                    "minL": {
                        "value": 80,
                        "type": "integer"
                    },
                    "maxL": {
                        "value": 100,
                        "type": "integer"
                    },
                    "mode": {
                        "value": "merged",
                        "type": "categorical"
                    }
                }
            }
        },
        {
            "modelOptions": {
                "type": "statistics",
                "name": "Grubbs test",
                "requiresPriorTraining": false,
                "isMultivariate": false,
                "outputsLabels": true,
                "useSubsequences": false,
                "hyperparameters": {
                    "alpha": {
                        "value": 0.5,
                        "type": "real"
                    }
                }
            }
        },
        {
            "modelOptions": {
                "type": "statistics",
                "name": "over-sampling PCA",
                "dataType": 1,
                "requiresPriorTraining": false,
                "isMultivariate": true,
                "outputsLabels": false,
                "useSubsequences": true,
                "hyperparameters": {
                    "ratioOversample": {
                        "value": 0.1,
                        "type": "real"
                    },
                    "windowSize": {
                        "value": 100,
                        "type": "integer"
                    }
                }
            }
        }
    ]
}
