{
    "models": [
        {
            "modelOptions": {
                "type": "deep-learning",
                "name": "FC-AE",
                "modelType": "reconstructive",
                "dataType": 1,
                "learningType": "semi-supervised",
                "isMultivariate": true,
                "outputsLabels": false,
                "hyperparameters": {
                    "neurons": 32,
                    "windowSize": 100,
                    "stepSize": 1,
                    "epochs": 50,
                    "learningRate": 0.001,
                    "minibatchSize": 64,
                    "ratioTrainVal": 0,
                    "reconstructionErrorType": "median point-wise values",
                    "scoringFunction": "aggregated-errors"
                }
            }
        },
        {
            "modelOptions": {
                "type": "deep-learning",
                "name": "LSTM (reconstruction)",
                "modelType": "reconstructive",
                "dataType": 2,
                "learningType": "semi-supervised",
                "isMultivariate": true,
                "outputsLabels": false,
                "hyperparameters": {
                    "hiddenUnits": 64,
                    "windowSize": 100,
                    "stepSize": 1,
                    "epochs": 50,
                    "learningRate": 0.001,
                    "minibatchSize": 64,
                    "ratioTrainVal": 0,
                    "reconstructionErrorType": "median point-wise values",
                    "scoringFunction": "aggregated-errors"
                }
            }
        },
        {
            "modelOptions": {
                "type": "deep-learning",
                "name": "Hybrid CNN-LSTM (reconstruction)",
                "modelType": "reconstructive",
                "dataType": 2,
                "learningType": "semi-supervised",
                "isMultivariate": true,
                "outputsLabels": false,
                "hyperparameters": {
                    "hiddenUnits": 64,
                    "filter": 32,
                    "windowSize": 100,
                    "stepSize": 1,
                    "epochs": 50,
                    "learningRate": 0.001,
                    "minibatchSize": 64,
                    "ratioTrainVal": 0,
                    "reconstructionErrorType": "median point-wise values",
                    "scoringFunction": "aggregated-errors"
                }
            }
        },
        {
            "modelOptions": {
                "type": "deep-learning",
                "name": "TCN-AE",
                "modelType": "reconstructive",
                "dataType": 2,
                "learningType": "semi-supervised",
                "isMultivariate": true,
                "outputsLabels": false,
                "hyperparameters": {
                    "filter": 32,
                    "windowSize": 100,
                    "stepSize": 1,
                    "epochs": 50,
                    "learningRate": 0.001,
                    "minibatchSize": 64,
                    "ratioTrainVal": 0,
                    "reconstructionErrorType": "median point-wise values",
                    "scoringFunction": "aggregated-errors"
                }
            }
        },
        {
            "modelOptions": {
                "type": "deep-learning",
                "name": "LSTM",
                "modelType": "predictive",
                "dataType": 2,
                "learningType": "semi-supervised",
                "isMultivariate": true,
                "outputsLabels": false,
                "hyperparameters": {
                    "hiddenUnits": 64,
                    "windowSize": 100,
                    "stepSize": 1,
                    "epochs": 50,
                    "learningRate": 0.001,
                    "minibatchSize": 64,
                    "ratioTrainVal": 0,
                    "scoringFunction": "aggregated-errors"
                }
            }
        },
        {
            "modelOptions": {
                "type": "deep-learning",
                "name": "Hybrid CNN-LSTM",
                "modelType": "predictive",
                "dataType": 2,
                "learningType": "semi-supervised",
                "isMultivariate": true,
                "outputsLabels": false,
                "hyperparameters": {
                    "hiddenUnits": 64,
                    "filter": 32,
                    "windowSize": 100,
                    "stepSize": 1,
                    "epochs": 50,
                    "learningRate": 0.001,
                    "minibatchSize": 64,
                    "ratioTrainVal": 0,
                    "scoringFunction": "aggregated-errors"
                }
            }
        },
        {
            "modelOptions": {
                "type": "deep-learning",
                "name": "GRU",
                "modelType": "predictive",
                "dataType": 2,
                "learningType": "semi-supervised",
                "isMultivariate": true,
                "outputsLabels": false,
                "hyperparameters": {
                    "hiddenUnits": 64,
                    "windowSize": 100,
                    "stepSize": 1,
                    "epochs": 50,
                    "learningRate": 0.001,
                    "minibatchSize": 64,
                    "ratioTrainVal": 0,
                    "scoringFunction": "aggregated-errors"
                }
            }
        },
        {
            "modelOptions": {
                "type": "deep-learning",
                "name": "CNN (DeepAnT)",
                "modelType": "predictive",
                "dataType": 3,
                "learningType": "semi-supervised",
                "isMultivariate": true,
                "outputsLabels": false,
                "hyperparameters": {
                    "filter": 8,
                    "windowSize": 100,
                    "stepSize": 1,
                    "epochs": 50,
                    "learningRate": 0.001,
                    "minibatchSize": 64,
                    "ratioTrainVal": 0,
                    "scoringFunction": "aggregated-errors"
                }
            }
        },
        {
            "modelOptions": {
                "type": "deep-learning",
                "name": "ResNet",
                "modelType": "predictive",
                "dataType": 3,
                "learningType": "semi-supervised",
                "isMultivariate": true,
                "outputsLabels": false,
                "hyperparameters": {
                    "filter": 32,
                    "windowSize": 100,
                    "stepSize": 1,
                    "epochs": 50,
                    "learningRate": 0.001,
                    "minibatchSize": 64,
                    "ratioTrainVal": 0,
                    "scoringFunction": "aggregated-errors"
                }
            }
        },
        {
            "modelOptions": {
                "type": "deep-learning",
                "name": "MLP",
                "modelType": "predictive",
                "dataType": 1,
                "learningType": "semi-supervised",
                "isMultivariate": true,
                "outputsLabels": false,
                "hyperparameters": {
                    "neurons": 32,
                    "windowSize": 100,
                    "stepSize": 1,
                    "epochs": 50,
                    "learningRate": 0.001,
                    "minibatchSize": 64,
                    "ratioTrainVal": 0,
                    "scoringFunction": "aggregated-errors"
                }
            }
        },
        {
            "modelOptions": {
                "type": "classic-machine-learning",
                "name": "iForest",
                "dataType": 1,
                "learningType": "semi-supervised",
                "isMultivariate": true,
                "outputsLabels": false,
                "useSubsequences": true,
                "hyperparameters": {
                    "numLearners": 100,
                    "numObservationsPerLearner": 128,
                    "windowSize": 100
                }
            }
        },
        {
            "modelOptions": {
                "type": "classic-machine-learning",
                "name": "OC-SVM",
                "dataType": 1,
                "learningType": "unsupervised",
                "isMultivariate": true,
                "outputsLabels": true,
                "useSubsequences": true,
                "hyperparameters": {
                    "kernelFunction": "gaussian",
                    "windowSize": 100
                }
            }
        },
        {
            "modelOptions": {
                "type": "classic-machine-learning",
                "name": "ABOD",
                "dataType": 1,
                "learningType": "unsupervised",
                "isMultivariate": true,
                "outputsLabels": false,
                "useSubsequences": true,
                "hyperparameters": {
                    "windowSize": 100
                }
            }
        },
        {
            "modelOptions": {
                "type": "classic-machine-learning",
                "name": "LOF",
                "dataType": 1,
                "learningType": "unsupervised",
                "isMultivariate": true,
                "outputsLabels": false,
                "useSubsequences": true,
                "hyperparameters": {
                    "k": 10,
                    "windowSize": 100
                }
            }
        },
        {
            "modelOptions": {
                "type": "classic-machine-learning",
                "name": "LDOF",
                "dataType": 1,
                "learningType": "unsupervised",
                "isMultivariate": true,
                "outputsLabels": false,
                "useSubsequences": true,
                "hyperparameters": {
                    "k": 10,
                    "windowSize": 100
                }
            }
        },
        {
            "modelOptions": {
                "type": "classic-machine-learning",
                "name": "Merlin",
                "learningType": "unsupervised",
                "isMultivariate": false,
                "outputsLabels": true,
                "useSubsequences": false,
                "hyperparameters": {
                    "minL": 90,
                    "maxL": 100,
                    "mode": "merged"
                }
            }
        },
        {
            "modelOptions": {
                "type": "classic-machine-learning",
                "name": "over-sampling PCA",
                "dataType": 1,
                "learningType": "unsupervised",
                "isMultivariate": true,
                "outputsLabels": false,
                "useSubsequences": true,
                "hyperparameters": {
                    "ratioOversample": 0.1,
                    "windowSize": 100
                }
            }
        },
        {
            "modelOptions": {
                "type": "statistics",
                "name": "Grubbs test",
                "learningType": "unsupervised",
                "isMultivariate": false,
                "outputsLabels": true,
                "useSubsequences": false,
                "hyperparameters": {
                    "alpha": 0.5
                }
            }
        }
    ]
}
